{"trial_id": "02", "hyperparameters": {"space": [{"class_name": "Int", "config": {"name": "units_lstm_1", "default": null, "conditions": [], "min_value": 1, "max_value": 600, "step": 1, "sampling": "linear"}}, {"class_name": "Float", "config": {"name": "dropout_1", "default": 0.001, "conditions": [], "min_value": 0.001, "max_value": 0.5, "step": null, "sampling": "linear"}}, {"class_name": "Int", "config": {"name": "units_lstm_2", "default": null, "conditions": [], "min_value": 1, "max_value": 600, "step": 1, "sampling": "linear"}}, {"class_name": "Float", "config": {"name": "dropout_2", "default": 0.001, "conditions": [], "min_value": 0.001, "max_value": 0.5, "step": null, "sampling": "linear"}}], "values": {"units_lstm_1": 64, "dropout_1": 0.03635014092387586, "units_lstm_2": 185, "dropout_2": 0.3000024086710482}}, "metrics": {"metrics": {"accuracy": {"direction": "max", "observations": [{"value": [0.8594940304756165], "step": 3}]}, "loss": {"direction": "min", "observations": [{"value": [0.09578244388103485], "step": 3}]}, "val_accuracy": {"direction": "max", "observations": [{"value": [0.7733287811279297], "step": 3}]}, "val_loss": {"direction": "min", "observations": [{"value": [0.1466408520936966], "step": 3}]}}}, "score": 0.8594940304756165, "best_step": 3, "status": "COMPLETED", "message": null}